weavedoc/__init__.py
weavedoc/weavedoc.py
weavedoc-0.0.1.dist-info/LICENSE
weavedoc-0.0.1.dist-info/METADATA
weavedoc-0.0.1.dist-info/WHEEL
weavedoc-0.0.1.dist-info/top_level.txt
weavedoc-0.0.1.dist-info/RECORD
