Metadata-Version: 2.1
Name: weavedoc
Version: 0.0.1
Summary: Static website generator for Markdown using YAML
Author-email: Erik Kamsties <weavedoc@example.com>
License: GNU GENERAL PUBLIC LICENSE
Project-URL: Homepage, https://github.com/pypa/weavedoc
Project-URL: Bug Tracker, https://github.com/pypa/weavedoc/issues
Classifier: Programming Language :: Python :: 3
Classifier: License :: OSI Approved :: GNU General Public License v3 or later (GPLv3+)
Classifier: Operating System :: OS Independent
Requires-Python: >=3.7
License-File: LICENSE
